easypip/__init__.py
easypip/_version.py
easypip/platform.py
easypip-1.4.1.dist-info/METADATA
easypip-1.4.1.dist-info/WHEEL
easypip-1.4.1.dist-info/top_level.txt
easypip-1.4.1.dist-info/RECORD
