Metadata-Version: 2.4
Name: easypip
Version: 1.4.1
Summary: Allows easier and lighter pip install within notebooks
Author-email: Benjamin Piwowarski <benjamin@piwowarski.fr>
Project-URL: homepage, https://github.com/bpiwowar/easypip
Requires-Dist: packaging
